cis_checks/__init__.py
cis_checks/iam_control_1.py
cis_checks/logging_control_2.py
cis_checks/monitoring_control_3.py
cis_checks/networking_control_4.py
cis_checks/security_control_5.py
cis_checks/utils.py
cis_checks-0.0.2.dist-info/METADATA
cis_checks-0.0.2.dist-info/WHEEL
cis_checks-0.0.2.dist-info/top_level.txt
cis_checks-0.0.2.dist-info/RECORD
